mqttools/__init__.py
mqttools/__main__.py
mqttools/broker.py
mqttools/client.py
mqttools/common.py
mqttools/version.py
mqttools/subparsers/__init__.py
mqttools/subparsers/broker.py
mqttools/subparsers/monitor.py
mqttools/subparsers/publish.py
mqttools/subparsers/subscribe.py
mqttools-0.47.0.dist-info/LICENSE
mqttools-0.47.0.dist-info/METADATA
mqttools-0.47.0.dist-info/WHEEL
mqttools-0.47.0.dist-info/entry_points.txt
mqttools-0.47.0.dist-info/top_level.txt
mqttools-0.47.0.dist-info/RECORD
