Metadata-Version: 2.1
Name: mqttools
Version: 0.47.0
Summary: MQTT tools.
Home-page: https://github.com/eerimoq/mqttools
Author: Erik Moqvist
Author-email: erik.moqvist@gmail.com
License: MIT
Keywords: mqtt
Platform: UNKNOWN
Classifier: License :: OSI Approved :: MIT License
Classifier: Programming Language :: Python :: 3
Requires-Dist: bitstruct
Requires-Dist: humanfriendly
Requires-Dist: argparse-addons
Requires-Dist: windows-curses ; platform_system == "Windows"
